Metadata-Version: 2.4
Name: autolamella
Version: 0.4.0
Summary: Automatated ion beam milling for cryo-electron microscopy sample preparation.
Author-email: Patrick Cleeve <patrick@openfibsem.org>
License: MIT License
Project-URL: Homepage, https://github.com/DeMarcoLab/autolamella
Project-URL: Bug Tracker, https://github.com/DeMarcoLab/autolamella/issues
Classifier: Programming Language :: Python :: 3.8
Classifier: License :: OSI Approved :: MIT License
Classifier: Operating System :: OS Independent
Classifier: Framework :: napari
Requires-Python: >=3.8
License-File: LICENSE
Requires-Dist: fibsem>=0.4.0
Dynamic: license-file
